Workbook

Sheet Summary
B2: ROBONEXA — Inventory Summary
B3: Auto-calculated from the Inventory sheet. Fill the Inventory + Vendors tabs; these update themselves.
B5: Total SKUs | E5: =COUNTA(Inventory!A2:A1000)
B6: Total stock value (at cost) | E6: =SUMPRODUCT(Inventory!E2:E1000,Inventory!K2:K1000)
B7: Total retail value (at selling) | E7: =SUMPRODUCT(Inventory!F2:F1000,Inventory!K2:K1000)
B8: Items to reorder (stock <= reorder level) | E8: =COUNTIF(Inventory!Q2:Q1000,"Reorder")
B9: Items out of stock | E9: =COUNTIF(Inventory!Q2:Q1000,"Out of stock")

Sheet Inventory
A1: SKU | B1: Product Name | C1: Category | D1: Vendor | E1: Cost Price (INR) | F1: Selling Price (INR) | G1: MRP (INR) | H1: Margin % | I1: GST % | J1: HSN Code | K1: Current Stock | L1: Reorder Level | M1: Reorder Qty | N1: Lead Time (days) | O1: Location / Bin | P1: Country of Origin | Q1: Status | R1: Reorder Alert | S1: Notes
A2: ACT-J60 | B2: QDD Joint Actuator ACT-J60 | C2: Actuators & Motors | D2: Vendor A | E2: 12000 | F2: 18500 | G2: 22000 | H2: =IF(F2=0,0,(F2-E2)/F2) | I2: 18 | J2: 85015210 | K2: 40 | L2: 10 | M2: 50 | N2: 20 | O2: Rack A-1 | P2: India | Q2: =IF(K2<=0,"Out of stock",IF(K2<=L2,"Reorder","In stock")) | R2: =IF(K2<=0,"OUT - call "&D2,IF(K2<=L2,"Reorder - call "&D2,"OK"))
A3: BLDC-200 | B3: BLDC Servo Gearmotor BLDC-200 | C3: Actuators & Motors | D3: Vendor A | E3: 6500 | F3: 9800 | G3: 12000 | H3: =IF(F3=0,0,(F3-E3)/F3) | I3: 18 | J3: 85015210 | K3: 85 | L3: 20 | M3: 100 | N3: 15 | O3: Rack A-2 | P3: India | Q3: =IF(K3<=0,"Out of stock",IF(K3<=L3,"Reorder","In stock")) | R3: =IF(K3<=0,"OUT - call "&D3,IF(K3<=L3,"Reorder - call "&D3,"OK"))
A4: DRV-48 | B4: FOC Servo Drive DRV-48 | C4: Drives & Controllers | D4: Vendor B | E4: 9000 | F4: 14500 | G4: 16900 | H4: =IF(F4=0,0,(F4-E4)/F4) | I4: 18 | J4: 85044090 | K4: 60 | L4: 15 | M4: 60 | N4: 25 | O4: Rack B-1 | P4: China | Q4: =IF(K4<=0,"Out of stock",IF(K4<=L4,"Reorder","In stock")) | R4: =IF(K4<=0,"OUT - call "&D4,IF(K4<=L4,"Reorder - call "&D4,"OK"))
A5: USBCAN-FD | B5: USB-to-CAN FD Adapter | C5: Drives & Controllers | D5: Vendor B | E5: 2200 | F5: 3900 | G5: 4600 | H5: =IF(F5=0,0,(F5-E5)/F5) | I5: 18 | J5: 85176290 | K5: 120 | L5: 30 | M5: 100 | N5: 20 | O5: Drawer B-3 | P5: China | Q5: =IF(K5<=0,"Out of stock",IF(K5<=L5,"Reorder","In stock")) | R5: =IF(K5<=0,"OUT - call "&D5,IF(K5<=L5,"Reorder - call "&D5,"OK"))
A6: LDR-32 | B6: 3D LiDAR LDR-32 (32-channel) | C6: Sensors & LiDAR | D6: Vendor C | E6: 130000 | F6: 185000 | G6: 210000 | H6: =IF(F6=0,0,(F6-E6)/F6) | I6: 18 | J6: 90318000 | K6: 0 | L6: 3 | M6: 10 | N6: 30 | O6: Cabinet C-1 | P6: China | Q6: =IF(K6<=0,"Out of stock",IF(K6<=L6,"Reorder","In stock")) | R6: =IF(K6<=0,"OUT - call "&D6,IF(K6<=L6,"Reorder - call "&D6,"OK"))
A7: ENC-19 | B7: Absolute Encoder ENC-19 | C7: Sensors & LiDAR | D7: Vendor C | E7: 4200 | F7: 6200 | G7: 7500 | H7: =IF(F7=0,0,(F7-E7)/F7) | I7: 18 | J7: 90318000 | K7: 150 | L7: 40 | M7: 100 | N7: 20 | O7: Drawer C-2 | P7: Germany | Q7: =IF(K7<=0,"Out of stock",IF(K7<=L7,"Reorder","In stock")) | R7: =IF(K7<=0,"OUT - call "&D7,IF(K7<=L7,"Reorder - call "&D7,"OK"))
A8: DCAM-S | B8: Stereo Depth Camera DCAM-S | C8: Sensors & LiDAR | D8: Vendor C | E8: 22000 | F8: 32000 | G8: 36000 | H8: =IF(F8=0,0,(F8-E8)/F8) | I8: 18 | J8: 85258900 | K8: 18 | L8: 5 | M8: 20 | N8: 25 | O8: Cabinet C-3 | P8: China | Q8: =IF(K8<=0,"Out of stock",IF(K8<=L8,"Reorder","In stock")) | R8: =IF(K8<=0,"OUT - call "&D8,IF(K8<=L8,"Reorder - call "&D8,"OK"))
A9: BAT-4820 | B9: 48V 20Ah LiFePO4 Battery Pack | C9: Power & Batteries | D9: Vendor D | E9: 19000 | F9: 28000 | G9: 0 | H9: =IF(F9=0,0,(F9-E9)/F9) | I9: 18 | J9: 85076000 | K9: 22 | L9: 6 | M9: 20 | N9: 18 | O9: Bay D-1 | P9: India | Q9: =IF(K9<=0,"Out of stock",IF(K9<=L9,"Reorder","In stock")) | R9: =IF(K9<=0,"OUT - call "&D9,IF(K9<=L9,"Reorder - call "&D9,"OK"))
A10: MEC-100 | B10: Mecanum Wheel Set (4x100mm) | C10: Wheels & Kits | D10: Vendor E | E10: 3600 | F10: 5400 | G10: 6800 | H10: =IF(F10=0,0,(F10-E10)/F10) | I10: 18 | J10: 87089900 | K10: 70 | L10: 20 | M10: 80 | N10: 15 | O10: Rack E-1 | P10: India | Q10: =IF(K10<=0,"Out of stock",IF(K10<=L10,"Reorder","In stock")) | R10: =IF(K10<=0,"OUT - call "&D10,IF(K10<=L10,"Reorder - call "&D10,"OK"))
A11: AMR-500 | B11: Autonomous Mobile Robot AMR-500 | C11: Robots & AMRs | D11: In-house | E11: 320000 | F11: 450000 | G11: 499000 | H11: =IF(F11=0,0,(F11-E11)/F11) | I11: 18 | J11: 84289090 | K11: 0 | L11: 1 | M11: 3 | N11: 20 | O11: Assembly | P11: India | Q11: =IF(K11<=0,"Out of stock",IF(K11<=L11,"Reorder","In stock")) | R11: =IF(K11<=0,"OUT - call "&D11,IF(K11<=L11,"Reorder - call "&D11,"OK"))
A12: ARM6-12 | B12: 6-Axis Collaborative Arm ARM6-12 | C12: Robots & AMRs | D12: Vendor F | E12: 520000 | F12: 690000 | G12: 749000 | H12: =IF(F12=0,0,(F12-E12)/F12) | I12: 18 | J12: 84795000 | K12: 2 | L12: 1 | M12: 2 | N12: 30 | O12: Assembly | P12: India | Q12: =IF(K12<=0,"Out of stock",IF(K12<=L12,"Reorder","In stock")) | R12: =IF(K12<=0,"OUT - call "&D12,IF(K12<=L12,"Reorder - call "&D12,"OK"))
A13: QP-20 | B13: Quadruped Platform QP-20 | C13: Robots & AMRs | D13: In-house | E13: 210000 | F13: 280000 | G13: 0 | H13: =IF(F13=0,0,(F13-E13)/F13) | I13: 18 | J13: 84795000 | K13: 1 | L13: 1 | M13: 2 | N13: 30 | O13: Assembly | P13: India | Q13: =IF(K13<=0,"Out of stock",IF(K13<=L13,"Reorder","In stock")) | R13: =IF(K13<=0,"OUT - call "&D13,IF(K13<=L13,"Reorder - call "&D13,"OK"))

Sheet Vendors
A1: Vendor ID | B1: Vendor Name | C1: Contact Person | D1: Phone | E1: Email | F1: GSTIN | G1: Address | H1: City | I1: State | J1: Products Supplied | K1: Lead Time (days) | L1: Payment Terms | M1: Rating (1-5) | N1: Notes
A2: Vendor A | H2: Pune | I2: Maharashtra | J2: Actuators, motors | K2: 20 | L2: Advance / 30 days
A3: Vendor B | J3: Drives, adapters | K3: 25
A4: Vendor C | J4: LiDAR, sensors, cameras | K4: 30
A5: Vendor D | J5: Batteries | K5: 18
A6: Vendor E | J6: Wheels, mechanical | K6: 15
A7: Vendor F | J7: Robot arms | K7: 30

Sheet Orders Log
A1: Order ID | B1: Date | C1: Customer | D1: Phone | E1: City | F1: State | G1: Items | H1: Total (INR) | I1: Payment Mode | J1: UPI / Txn Ref | K1: Status | L1: Delivery ETA | M1: Tracking | N1: Notes
A2: ORD-000001 | B2: 2026-09-21 | C2: Example Customer | E2: Pune | F2: Maharashtra | G2: ACT-J60 x2 | H2: 37000 | I2: UPI | K2: Placed | L2: 2026-09-23 | N2: Sample row — delete
